deepd3/__init__.py
deepd3/core/__init__.py
deepd3/core/analysis.py
deepd3/core/dendrite.py
deepd3/core/distance.py
deepd3/core/export.py
deepd3/core/spines.py
deepd3/inference/__init__.py
deepd3/inference/batch.py
deepd3/inference/gui.py
deepd3/model/__init__.py
deepd3/model/builder.py
deepd3/model/utils.py
deepd3/training/__init__.py
deepd3/training/generator.py
deepd3/training/stream.py
deepd3-0.1.dist-info/LICENSE
deepd3-0.1.dist-info/METADATA
deepd3-0.1.dist-info/WHEEL
deepd3-0.1.dist-info/entry_points.txt
deepd3-0.1.dist-info/top_level.txt
deepd3-0.1.dist-info/RECORD
