Metadata-Version: 2.1
Name: deepd3
Version: 0.1
Summary: A tool for segmenting dendrites and dendritic spines.
Author: Andreas M Kist
Author-email: andreas.kist@fau.de
License: GPLv3
Project-URL: Source, https://github.com/ankilab/deepd3
Project-URL: Tracker, https://github.com/ankilab/deepd3/issues
Keywords: spine segmentation
Classifier: Development Status :: 4 - Beta
Classifier: Intended Audience :: Science/Research
Classifier: License :: OSI Approved :: GNU General Public License v3 or later (GPLv3+)
Classifier: Programming Language :: Python :: 3.6
Classifier: Programming Language :: Python :: 3.7
Classifier: Programming Language :: Python :: 3.8
License-File: LICENSE
Requires-Dist: pyqtgraph (>=0.10.0)
Requires-Dist: numpy
Requires-Dist: numba
Requires-Dist: flammkuchen
Requires-Dist: pyqt5
Requires-Dist: scikit-image
Requires-Dist: imageio
Requires-Dist: imageio-ffmpeg
Requires-Dist: opencv-python
Requires-Dist: pandas
Requires-Dist: tqdm
Requires-Dist: roifile
Requires-Dist: segmentation-models
Requires-Dist: connected-components-3d
Requires-Dist: albumentations
